{"2t": [[2222, 3], [15715, 2], [16270, 2], [16840, 1], [17878, 2], [20339, 5]], "2tb": [[3530, 1], [3562, 1]], "2tango": [[4534, 1]], "2time": [[5666, 1], [8437, 1]], "2thi": [[6022, 1], [8977, 1], [9962, 1]], "2team": [[7236, 1], [8184, 1]], "2type": [[7659, 1], [10542, 1]], "2tlwlc": [[8035, 1], [8595, 1]], "2taoizonnpo": [[8595, 1]], "2tuesday": [[13292, 1]], "2thursday": [[13292, 1]], "2the": [[17098, 500], [20369, 1], [20684, 1]], "2tlvjpkafazzfblcmuk0gq5q3rsue8w9jxrboj01tucz1eyvxa": [[17757, 1]], "2tcnq": [[17757, 1]], "2tue": [[17975, 1]], "2text": [[18248, 1]]}